<?xml version='1.0' encoding='UTF-8'?>
<data>
<AD_ORG_CLOSING>
  <AD_ORG_CLOSING_ID><![CDATA[020B4978F62A4AEC8344CE7A45F25DAD]]></AD_ORG_CLOSING_ID>
  <AD_CLIENT_ID><![CDATA[23C59575B9CF467C9620760EB255B389]]></AD_CLIENT_ID>
  <AD_ORG_ID><![CDATA[2E60544D37534C0B89E765FE29BC0B43]]></AD_ORG_ID>
  <ISACTIVE><![CDATA[Y]]></ISACTIVE>
  <CREATED><![CDATA[2019-03-20 22:48:44.746092]]></CREATED>
  <CREATEDBY><![CDATA[100]]></CREATEDBY>
  <UPDATED><![CDATA[2019-03-20 22:48:44.746092]]></UPDATED>
  <UPDATEDBY><![CDATA[100]]></UPDATEDBY>
  <C_YEAR_ID><![CDATA[9BE65A3164D142F493A6B1D60DE385B9]]></C_YEAR_ID>
  <AD_ORG_ACCTSCHEMA_ID><![CDATA[B6D5FF3A416C4371851ADA64EE9F0674]]></AD_ORG_ACCTSCHEMA_ID>
  <REG_FACT_ACCT_GROUP_ID><![CDATA[11C98C7F52254D6A87E139981CE3BC7E]]></REG_FACT_ACCT_GROUP_ID>
  <CLOSE_FACT_ACCT_GROUP_ID><![CDATA[9EAE4659AC15419693EBAE94BF4CC9B2]]></CLOSE_FACT_ACCT_GROUP_ID>
  <DIVIDEUP_FACT_ACCT_GROUP_ID><![CDATA[ECB2A26E521E4E4F9CE4F6030CBEA2CE]]></DIVIDEUP_FACT_ACCT_GROUP_ID>
  <OPEN_FACT_ACCT_GROUP_ID><![CDATA[09C2339CE27A458EA76CC96ADFCA2142]]></OPEN_FACT_ACCT_GROUP_ID>
</AD_ORG_CLOSING>

<AD_ORG_CLOSING>
  <AD_ORG_CLOSING_ID><![CDATA[1E7B50EED69C4A4F968D2247A8551C57]]></AD_ORG_CLOSING_ID>
  <AD_CLIENT_ID><![CDATA[23C59575B9CF467C9620760EB255B389]]></AD_CLIENT_ID>
  <AD_ORG_ID><![CDATA[B843C30461EA4501935CB1D125C9C25A]]></AD_ORG_ID>
  <ISACTIVE><![CDATA[Y]]></ISACTIVE>
  <CREATED><![CDATA[2019-03-20 22:48:34.582603]]></CREATED>
  <CREATEDBY><![CDATA[100]]></CREATEDBY>
  <UPDATED><![CDATA[2019-03-20 22:48:34.582603]]></UPDATED>
  <UPDATEDBY><![CDATA[100]]></UPDATEDBY>
  <C_YEAR_ID><![CDATA[138329A31E67498287DEFD3D963143BB]]></C_YEAR_ID>
  <AD_ORG_ACCTSCHEMA_ID><![CDATA[7583C0C800F14661B348A271ED276A14]]></AD_ORG_ACCTSCHEMA_ID>
  <REG_FACT_ACCT_GROUP_ID><![CDATA[FCB51FD745564CF3AB41B5318CAD1CB4]]></REG_FACT_ACCT_GROUP_ID>
  <CLOSE_FACT_ACCT_GROUP_ID><![CDATA[5805ABDF6C1E4183B7DFCCA35BFF385F]]></CLOSE_FACT_ACCT_GROUP_ID>
  <OPEN_FACT_ACCT_GROUP_ID><![CDATA[0ED62928088E4A9A8118711E2DCABA57]]></OPEN_FACT_ACCT_GROUP_ID>
</AD_ORG_CLOSING>

<AD_ORG_CLOSING>
  <AD_ORG_CLOSING_ID><![CDATA[2A00465CDEFC48CEADA81D0B3985E8E3]]></AD_ORG_CLOSING_ID>
  <AD_CLIENT_ID><![CDATA[23C59575B9CF467C9620760EB255B389]]></AD_CLIENT_ID>
  <AD_ORG_ID><![CDATA[B843C30461EA4501935CB1D125C9C25A]]></AD_ORG_ID>
  <ISACTIVE><![CDATA[Y]]></ISACTIVE>
  <CREATED><![CDATA[2019-03-20 22:48:56.683402]]></CREATED>
  <CREATEDBY><![CDATA[100]]></CREATEDBY>
  <UPDATED><![CDATA[2019-03-20 22:48:56.683402]]></UPDATED>
  <UPDATEDBY><![CDATA[100]]></UPDATEDBY>
  <C_YEAR_ID><![CDATA[BDDA2F60FE294C228DC7CFC3291D5ADF]]></C_YEAR_ID>
  <AD_ORG_ACCTSCHEMA_ID><![CDATA[7583C0C800F14661B348A271ED276A14]]></AD_ORG_ACCTSCHEMA_ID>
  <REG_FACT_ACCT_GROUP_ID><![CDATA[27A0580FDBC44E1597C9A9676F5CB13B]]></REG_FACT_ACCT_GROUP_ID>
  <CLOSE_FACT_ACCT_GROUP_ID><![CDATA[B4D8B811636641D998BE0E0FA303EB00]]></CLOSE_FACT_ACCT_GROUP_ID>
  <OPEN_FACT_ACCT_GROUP_ID><![CDATA[35D638D210D64E96839685715553F895]]></OPEN_FACT_ACCT_GROUP_ID>
</AD_ORG_CLOSING>

<AD_ORG_CLOSING>
  <AD_ORG_CLOSING_ID><![CDATA[33494205410E4616BDA1C7DEEC09ED4F]]></AD_ORG_CLOSING_ID>
  <AD_CLIENT_ID><![CDATA[23C59575B9CF467C9620760EB255B389]]></AD_CLIENT_ID>
  <AD_ORG_ID><![CDATA[2E60544D37534C0B89E765FE29BC0B43]]></AD_ORG_ID>
  <ISACTIVE><![CDATA[Y]]></ISACTIVE>
  <CREATED><![CDATA[2021-03-29 21:06:19.474997]]></CREATED>
  <CREATEDBY><![CDATA[100]]></CREATEDBY>
  <UPDATED><![CDATA[2021-03-29 21:06:19.474997]]></UPDATED>
  <UPDATEDBY><![CDATA[100]]></UPDATEDBY>
  <C_YEAR_ID><![CDATA[1E4627A75214474084A55D433FA060F6]]></C_YEAR_ID>
  <AD_ORG_ACCTSCHEMA_ID><![CDATA[B6D5FF3A416C4371851ADA64EE9F0674]]></AD_ORG_ACCTSCHEMA_ID>
  <REG_FACT_ACCT_GROUP_ID><![CDATA[FD40CED3F79A4B238BA420A08F006E50]]></REG_FACT_ACCT_GROUP_ID>
  <CLOSE_FACT_ACCT_GROUP_ID><![CDATA[82ABE2B84F154B9D817C160F3174F51F]]></CLOSE_FACT_ACCT_GROUP_ID>
  <DIVIDEUP_FACT_ACCT_GROUP_ID><![CDATA[DA4CE263856D4591932527033C1B5091]]></DIVIDEUP_FACT_ACCT_GROUP_ID>
  <OPEN_FACT_ACCT_GROUP_ID><![CDATA[1A810E3CB298475F97A55C28341B35F6]]></OPEN_FACT_ACCT_GROUP_ID>
</AD_ORG_CLOSING>

<AD_ORG_CLOSING>
  <AD_ORG_CLOSING_ID><![CDATA[3AB2B1E7A62745A0A36CAFB617CCB58F]]></AD_ORG_CLOSING_ID>
  <AD_CLIENT_ID><![CDATA[23C59575B9CF467C9620760EB255B389]]></AD_CLIENT_ID>
  <AD_ORG_ID><![CDATA[B843C30461EA4501935CB1D125C9C25A]]></AD_ORG_ID>
  <ISACTIVE><![CDATA[Y]]></ISACTIVE>
  <CREATED><![CDATA[2019-03-20 22:48:52.433918]]></CREATED>
  <CREATEDBY><![CDATA[100]]></CREATEDBY>
  <UPDATED><![CDATA[2019-03-20 22:48:52.433918]]></UPDATED>
  <UPDATEDBY><![CDATA[100]]></UPDATEDBY>
  <C_YEAR_ID><![CDATA[8145E65C9078438681F06187E84E4C40]]></C_YEAR_ID>
  <AD_ORG_ACCTSCHEMA_ID><![CDATA[B6D5FF3A416C4371851ADA64EE9F0674]]></AD_ORG_ACCTSCHEMA_ID>
  <REG_FACT_ACCT_GROUP_ID><![CDATA[85B3F42C36E140EC9A241AD90805D277]]></REG_FACT_ACCT_GROUP_ID>
  <CLOSE_FACT_ACCT_GROUP_ID><![CDATA[C056F48AAAD44F1D98A2E052933F2E45]]></CLOSE_FACT_ACCT_GROUP_ID>
  <DIVIDEUP_FACT_ACCT_GROUP_ID><![CDATA[C964897BE19649CA9BBDD6A3E8FC891C]]></DIVIDEUP_FACT_ACCT_GROUP_ID>
  <OPEN_FACT_ACCT_GROUP_ID><![CDATA[9A6649D65F804297804845C7A2614EC6]]></OPEN_FACT_ACCT_GROUP_ID>
</AD_ORG_CLOSING>

<AD_ORG_CLOSING>
  <AD_ORG_CLOSING_ID><![CDATA[4B0354386C9D49DAAF987948A446EBD1]]></AD_ORG_CLOSING_ID>
  <AD_CLIENT_ID><![CDATA[23C59575B9CF467C9620760EB255B389]]></AD_CLIENT_ID>
  <AD_ORG_ID><![CDATA[2E60544D37534C0B89E765FE29BC0B43]]></AD_ORG_ID>
  <ISACTIVE><![CDATA[Y]]></ISACTIVE>
  <CREATED><![CDATA[2021-03-29 21:06:27.856799]]></CREATED>
  <CREATEDBY><![CDATA[100]]></CREATEDBY>
  <UPDATED><![CDATA[2021-03-29 21:06:27.856799]]></UPDATED>
  <UPDATEDBY><![CDATA[100]]></UPDATEDBY>
  <C_YEAR_ID><![CDATA[B78696C8AAEB49368A426A5E4DC4BE3B]]></C_YEAR_ID>
  <AD_ORG_ACCTSCHEMA_ID><![CDATA[B6D5FF3A416C4371851ADA64EE9F0674]]></AD_ORG_ACCTSCHEMA_ID>
  <REG_FACT_ACCT_GROUP_ID><![CDATA[613717628C7C4441A09540E877B06DB2]]></REG_FACT_ACCT_GROUP_ID>
  <CLOSE_FACT_ACCT_GROUP_ID><![CDATA[4434ABBD1858473DA3BC1D8F8390FDC6]]></CLOSE_FACT_ACCT_GROUP_ID>
  <DIVIDEUP_FACT_ACCT_GROUP_ID><![CDATA[77C536C3A5EB4710B3E863CAEF549900]]></DIVIDEUP_FACT_ACCT_GROUP_ID>
  <OPEN_FACT_ACCT_GROUP_ID><![CDATA[CC8522358F0D43048F51F31D9A91327D]]></OPEN_FACT_ACCT_GROUP_ID>
</AD_ORG_CLOSING>

<AD_ORG_CLOSING>
  <AD_ORG_CLOSING_ID><![CDATA[53082C6969F145E49CA911A877C87BCF]]></AD_ORG_CLOSING_ID>
  <AD_CLIENT_ID><![CDATA[23C59575B9CF467C9620760EB255B389]]></AD_CLIENT_ID>
  <AD_ORG_ID><![CDATA[B843C30461EA4501935CB1D125C9C25A]]></AD_ORG_ID>
  <ISACTIVE><![CDATA[Y]]></ISACTIVE>
  <CREATED><![CDATA[2021-03-29 21:06:23.524707]]></CREATED>
  <CREATEDBY><![CDATA[100]]></CREATEDBY>
  <UPDATED><![CDATA[2021-03-29 21:06:23.524707]]></UPDATED>
  <UPDATEDBY><![CDATA[100]]></UPDATEDBY>
  <C_YEAR_ID><![CDATA[3DEC6A414B294F648D05AB2A9F61EEC6]]></C_YEAR_ID>
  <AD_ORG_ACCTSCHEMA_ID><![CDATA[7583C0C800F14661B348A271ED276A14]]></AD_ORG_ACCTSCHEMA_ID>
  <REG_FACT_ACCT_GROUP_ID><![CDATA[2EAB0DB2FF344BC2958DC178A7315D8F]]></REG_FACT_ACCT_GROUP_ID>
  <CLOSE_FACT_ACCT_GROUP_ID><![CDATA[66B1987B1784400BBA371947E251A25F]]></CLOSE_FACT_ACCT_GROUP_ID>
  <OPEN_FACT_ACCT_GROUP_ID><![CDATA[A9BB2F40246F403CA8EDA7DDB7CAE00F]]></OPEN_FACT_ACCT_GROUP_ID>
</AD_ORG_CLOSING>

<AD_ORG_CLOSING>
  <AD_ORG_CLOSING_ID><![CDATA[5F5E9E6D212A4779A7E6982B2B4779D4]]></AD_ORG_CLOSING_ID>
  <AD_CLIENT_ID><![CDATA[23C59575B9CF467C9620760EB255B389]]></AD_CLIENT_ID>
  <AD_ORG_ID><![CDATA[2E60544D37534C0B89E765FE29BC0B43]]></AD_ORG_ID>
  <ISACTIVE><![CDATA[Y]]></ISACTIVE>
  <CREATED><![CDATA[2019-03-20 22:48:18.206553]]></CREATED>
  <CREATEDBY><![CDATA[100]]></CREATEDBY>
  <UPDATED><![CDATA[2019-03-20 22:48:18.206553]]></UPDATED>
  <UPDATEDBY><![CDATA[100]]></UPDATEDBY>
  <C_YEAR_ID><![CDATA[3BAAC4D19AEC4D65AEAE90971468013F]]></C_YEAR_ID>
  <AD_ORG_ACCTSCHEMA_ID><![CDATA[B6D5FF3A416C4371851ADA64EE9F0674]]></AD_ORG_ACCTSCHEMA_ID>
  <REG_FACT_ACCT_GROUP_ID><![CDATA[E3E038ED7FCC4411AA6D5ECA991F8CC8]]></REG_FACT_ACCT_GROUP_ID>
  <CLOSE_FACT_ACCT_GROUP_ID><![CDATA[3929A67C7D0E40DBBF863C695B14C6F1]]></CLOSE_FACT_ACCT_GROUP_ID>
  <DIVIDEUP_FACT_ACCT_GROUP_ID><![CDATA[C4FE45A25FF04E3E8A66147EB02EF446]]></DIVIDEUP_FACT_ACCT_GROUP_ID>
  <OPEN_FACT_ACCT_GROUP_ID><![CDATA[DF81C9DEB55346E89B6005261AA6437B]]></OPEN_FACT_ACCT_GROUP_ID>
</AD_ORG_CLOSING>

<AD_ORG_CLOSING>
  <AD_ORG_CLOSING_ID><![CDATA[6A967E9FF32B4899B0CF0ACDCC0A5288]]></AD_ORG_CLOSING_ID>
  <AD_CLIENT_ID><![CDATA[23C59575B9CF467C9620760EB255B389]]></AD_CLIENT_ID>
  <AD_ORG_ID><![CDATA[2E60544D37534C0B89E765FE29BC0B43]]></AD_ORG_ID>
  <ISACTIVE><![CDATA[Y]]></ISACTIVE>
  <CREATED><![CDATA[2019-03-20 22:49:00.49363]]></CREATED>
  <CREATEDBY><![CDATA[100]]></CREATEDBY>
  <UPDATED><![CDATA[2019-03-20 22:49:00.49363]]></UPDATED>
  <UPDATEDBY><![CDATA[100]]></UPDATEDBY>
  <C_YEAR_ID><![CDATA[2B9E016BE5F94756ABD6CBABBD002219]]></C_YEAR_ID>
  <AD_ORG_ACCTSCHEMA_ID><![CDATA[B6D5FF3A416C4371851ADA64EE9F0674]]></AD_ORG_ACCTSCHEMA_ID>
  <REG_FACT_ACCT_GROUP_ID><![CDATA[27F68DF7EBE14F468D929815B530BC4B]]></REG_FACT_ACCT_GROUP_ID>
  <CLOSE_FACT_ACCT_GROUP_ID><![CDATA[B1AEE0AC31644B06840D7B2731A7A7EB]]></CLOSE_FACT_ACCT_GROUP_ID>
  <DIVIDEUP_FACT_ACCT_GROUP_ID><![CDATA[106A20581769476E8EAD3BC0F0F75123]]></DIVIDEUP_FACT_ACCT_GROUP_ID>
  <OPEN_FACT_ACCT_GROUP_ID><![CDATA[36B6D120A4D14E9C93905E055B0228B5]]></OPEN_FACT_ACCT_GROUP_ID>
</AD_ORG_CLOSING>

<AD_ORG_CLOSING>
  <AD_ORG_CLOSING_ID><![CDATA[7CAF3EA1D1B340D7B2B75E8692AF4C07]]></AD_ORG_CLOSING_ID>
  <AD_CLIENT_ID><![CDATA[23C59575B9CF467C9620760EB255B389]]></AD_CLIENT_ID>
  <AD_ORG_ID><![CDATA[2E60544D37534C0B89E765FE29BC0B43]]></AD_ORG_ID>
  <ISACTIVE><![CDATA[Y]]></ISACTIVE>
  <CREATED><![CDATA[2019-03-20 22:48:48.91276]]></CREATED>
  <CREATEDBY><![CDATA[100]]></CREATEDBY>
  <UPDATED><![CDATA[2019-03-20 22:48:48.91276]]></UPDATED>
  <UPDATEDBY><![CDATA[100]]></UPDATEDBY>
  <C_YEAR_ID><![CDATA[2ED071B397AB4BEF82BF3020C3F1948C]]></C_YEAR_ID>
  <AD_ORG_ACCTSCHEMA_ID><![CDATA[B6D5FF3A416C4371851ADA64EE9F0674]]></AD_ORG_ACCTSCHEMA_ID>
  <REG_FACT_ACCT_GROUP_ID><![CDATA[2714025B8F084D858E46230302075CFF]]></REG_FACT_ACCT_GROUP_ID>
  <CLOSE_FACT_ACCT_GROUP_ID><![CDATA[53C09C301E474473A360A167991A8BDF]]></CLOSE_FACT_ACCT_GROUP_ID>
  <DIVIDEUP_FACT_ACCT_GROUP_ID><![CDATA[B95E0DBB4B914EA3ABA0AD06D5FDF637]]></DIVIDEUP_FACT_ACCT_GROUP_ID>
  <OPEN_FACT_ACCT_GROUP_ID><![CDATA[07EDF27FDC414F979021D89187189EE8]]></OPEN_FACT_ACCT_GROUP_ID>
</AD_ORG_CLOSING>

<AD_ORG_CLOSING>
  <AD_ORG_CLOSING_ID><![CDATA[7CE33AFA03A34FB4A76380283EFDCAF6]]></AD_ORG_CLOSING_ID>
  <AD_CLIENT_ID><![CDATA[23C59575B9CF467C9620760EB255B389]]></AD_CLIENT_ID>
  <AD_ORG_ID><![CDATA[B843C30461EA4501935CB1D125C9C25A]]></AD_ORG_ID>
  <ISACTIVE><![CDATA[Y]]></ISACTIVE>
  <CREATED><![CDATA[2021-03-29 21:06:14.799758]]></CREATED>
  <CREATEDBY><![CDATA[100]]></CREATEDBY>
  <UPDATED><![CDATA[2021-03-29 21:06:14.799758]]></UPDATED>
  <UPDATEDBY><![CDATA[100]]></UPDATEDBY>
  <C_YEAR_ID><![CDATA[D8185F72B57749869DC219CF2D1E863A]]></C_YEAR_ID>
  <AD_ORG_ACCTSCHEMA_ID><![CDATA[7583C0C800F14661B348A271ED276A14]]></AD_ORG_ACCTSCHEMA_ID>
  <REG_FACT_ACCT_GROUP_ID><![CDATA[0CA2C94B172840D58C0DFF7F9E06F8EE]]></REG_FACT_ACCT_GROUP_ID>
  <CLOSE_FACT_ACCT_GROUP_ID><![CDATA[092F541AD21C4667A8F0D24F6C171F6C]]></CLOSE_FACT_ACCT_GROUP_ID>
  <OPEN_FACT_ACCT_GROUP_ID><![CDATA[318F75A9AB29437AB09C040240E79130]]></OPEN_FACT_ACCT_GROUP_ID>
</AD_ORG_CLOSING>

<AD_ORG_CLOSING>
  <AD_ORG_CLOSING_ID><![CDATA[7F36577903DA41D692F5698FB53C3BD5]]></AD_ORG_CLOSING_ID>
  <AD_CLIENT_ID><![CDATA[23C59575B9CF467C9620760EB255B389]]></AD_CLIENT_ID>
  <AD_ORG_ID><![CDATA[B843C30461EA4501935CB1D125C9C25A]]></AD_ORG_ID>
  <ISACTIVE><![CDATA[Y]]></ISACTIVE>
  <CREATED><![CDATA[2019-03-20 22:48:26.296703]]></CREATED>
  <CREATEDBY><![CDATA[100]]></CREATEDBY>
  <UPDATED><![CDATA[2019-03-20 22:48:26.296703]]></UPDATED>
  <UPDATEDBY><![CDATA[100]]></UPDATEDBY>
  <C_YEAR_ID><![CDATA[09E6CC5F7F6D4E8FA3DE5E120F7F9505]]></C_YEAR_ID>
  <AD_ORG_ACCTSCHEMA_ID><![CDATA[7583C0C800F14661B348A271ED276A14]]></AD_ORG_ACCTSCHEMA_ID>
  <REG_FACT_ACCT_GROUP_ID><![CDATA[CDC5201DACE144DB90EBBC9D6BFB3FDA]]></REG_FACT_ACCT_GROUP_ID>
  <CLOSE_FACT_ACCT_GROUP_ID><![CDATA[01E788095E1048359AE9BFD20DDBFAA9]]></CLOSE_FACT_ACCT_GROUP_ID>
  <OPEN_FACT_ACCT_GROUP_ID><![CDATA[2A26CA01ACA84C3A8736B98909A97BBE]]></OPEN_FACT_ACCT_GROUP_ID>
</AD_ORG_CLOSING>

<AD_ORG_CLOSING>
  <AD_ORG_CLOSING_ID><![CDATA[846690CAE1D54D2ABD6233DBA55715CA]]></AD_ORG_CLOSING_ID>
  <AD_CLIENT_ID><![CDATA[23C59575B9CF467C9620760EB255B389]]></AD_CLIENT_ID>
  <AD_ORG_ID><![CDATA[B843C30461EA4501935CB1D125C9C25A]]></AD_ORG_ID>
  <ISACTIVE><![CDATA[Y]]></ISACTIVE>
  <CREATED><![CDATA[2019-03-20 22:48:38.551315]]></CREATED>
  <CREATEDBY><![CDATA[100]]></CREATEDBY>
  <UPDATED><![CDATA[2019-03-20 22:48:38.551315]]></UPDATED>
  <UPDATEDBY><![CDATA[100]]></UPDATEDBY>
  <C_YEAR_ID><![CDATA[F2894E04910B4764B50A31BF018EBA8E]]></C_YEAR_ID>
  <AD_ORG_ACCTSCHEMA_ID><![CDATA[B6D5FF3A416C4371851ADA64EE9F0674]]></AD_ORG_ACCTSCHEMA_ID>
  <REG_FACT_ACCT_GROUP_ID><![CDATA[04639678E66845E2845A49CFEDDE12D4]]></REG_FACT_ACCT_GROUP_ID>
  <CLOSE_FACT_ACCT_GROUP_ID><![CDATA[6D3C03F8432D4F099215C67E8A509D8D]]></CLOSE_FACT_ACCT_GROUP_ID>
  <DIVIDEUP_FACT_ACCT_GROUP_ID><![CDATA[91387B8A357F455985B96724AF041613]]></DIVIDEUP_FACT_ACCT_GROUP_ID>
  <OPEN_FACT_ACCT_GROUP_ID><![CDATA[9A02398F8BF34C8687BC2B5259C361E3]]></OPEN_FACT_ACCT_GROUP_ID>
</AD_ORG_CLOSING>

<AD_ORG_CLOSING>
  <AD_ORG_CLOSING_ID><![CDATA[8E0A2EEEC4324F0CAA056ED21546FBEB]]></AD_ORG_CLOSING_ID>
  <AD_CLIENT_ID><![CDATA[23C59575B9CF467C9620760EB255B389]]></AD_CLIENT_ID>
  <AD_ORG_ID><![CDATA[2E60544D37534C0B89E765FE29BC0B43]]></AD_ORG_ID>
  <ISACTIVE><![CDATA[Y]]></ISACTIVE>
  <CREATED><![CDATA[2019-03-20 22:48:21.900571]]></CREATED>
  <CREATEDBY><![CDATA[100]]></CREATEDBY>
  <UPDATED><![CDATA[2019-03-20 22:48:21.900571]]></UPDATED>
  <UPDATEDBY><![CDATA[100]]></UPDATEDBY>
  <C_YEAR_ID><![CDATA[2B584DF89D2C4628AF0E391F07177F47]]></C_YEAR_ID>
  <AD_ORG_ACCTSCHEMA_ID><![CDATA[B6D5FF3A416C4371851ADA64EE9F0674]]></AD_ORG_ACCTSCHEMA_ID>
  <REG_FACT_ACCT_GROUP_ID><![CDATA[07DF241650384FD79EE820BAE96FEB6F]]></REG_FACT_ACCT_GROUP_ID>
  <CLOSE_FACT_ACCT_GROUP_ID><![CDATA[7DD1447D3C22477EB3802F6832767B75]]></CLOSE_FACT_ACCT_GROUP_ID>
  <DIVIDEUP_FACT_ACCT_GROUP_ID><![CDATA[8CE867E6D97D4AC9AB8E9BDEB1344D94]]></DIVIDEUP_FACT_ACCT_GROUP_ID>
  <OPEN_FACT_ACCT_GROUP_ID><![CDATA[60D1036019534A37925CCF291D69CDE5]]></OPEN_FACT_ACCT_GROUP_ID>
</AD_ORG_CLOSING>

<AD_ORG_CLOSING>
  <AD_ORG_CLOSING_ID><![CDATA[93551AC648134053A3AE25D9CB588590]]></AD_ORG_CLOSING_ID>
  <AD_CLIENT_ID><![CDATA[23C59575B9CF467C9620760EB255B389]]></AD_CLIENT_ID>
  <AD_ORG_ID><![CDATA[B843C30461EA4501935CB1D125C9C25A]]></AD_ORG_ID>
  <ISACTIVE><![CDATA[Y]]></ISACTIVE>
  <CREATED><![CDATA[2019-03-20 22:48:13.868739]]></CREATED>
  <CREATEDBY><![CDATA[100]]></CREATEDBY>
  <UPDATED><![CDATA[2019-03-20 22:48:13.868739]]></UPDATED>
  <UPDATEDBY><![CDATA[100]]></UPDATEDBY>
  <C_YEAR_ID><![CDATA[BE903865711D408390B24C366B6C4099]]></C_YEAR_ID>
  <AD_ORG_ACCTSCHEMA_ID><![CDATA[7583C0C800F14661B348A271ED276A14]]></AD_ORG_ACCTSCHEMA_ID>
  <REG_FACT_ACCT_GROUP_ID><![CDATA[D274AAB6B271475C91CAD7B203BCD9CE]]></REG_FACT_ACCT_GROUP_ID>
  <CLOSE_FACT_ACCT_GROUP_ID><![CDATA[898D512514DD425DB690214589B19F25]]></CLOSE_FACT_ACCT_GROUP_ID>
  <OPEN_FACT_ACCT_GROUP_ID><![CDATA[7A52C9ACB4C6479FA02331DCCEC41E29]]></OPEN_FACT_ACCT_GROUP_ID>
</AD_ORG_CLOSING>

<AD_ORG_CLOSING>
  <AD_ORG_CLOSING_ID><![CDATA[954000D496D54BD7885E00FED544964D]]></AD_ORG_CLOSING_ID>
  <AD_CLIENT_ID><![CDATA[23C59575B9CF467C9620760EB255B389]]></AD_CLIENT_ID>
  <AD_ORG_ID><![CDATA[B843C30461EA4501935CB1D125C9C25A]]></AD_ORG_ID>
  <ISACTIVE><![CDATA[Y]]></ISACTIVE>
  <CREATED><![CDATA[2019-03-20 22:48:34.582603]]></CREATED>
  <CREATEDBY><![CDATA[100]]></CREATEDBY>
  <UPDATED><![CDATA[2019-03-20 22:48:34.582603]]></UPDATED>
  <UPDATEDBY><![CDATA[100]]></UPDATEDBY>
  <C_YEAR_ID><![CDATA[138329A31E67498287DEFD3D963143BB]]></C_YEAR_ID>
  <AD_ORG_ACCTSCHEMA_ID><![CDATA[B6D5FF3A416C4371851ADA64EE9F0674]]></AD_ORG_ACCTSCHEMA_ID>
  <REG_FACT_ACCT_GROUP_ID><![CDATA[7D3B77828AA24330923CE673FF95F39E]]></REG_FACT_ACCT_GROUP_ID>
  <CLOSE_FACT_ACCT_GROUP_ID><![CDATA[2D28740694894806B567F239E8256360]]></CLOSE_FACT_ACCT_GROUP_ID>
  <DIVIDEUP_FACT_ACCT_GROUP_ID><![CDATA[038782B0DF72427083725A9908727D57]]></DIVIDEUP_FACT_ACCT_GROUP_ID>
  <OPEN_FACT_ACCT_GROUP_ID><![CDATA[BC73DC15CF394592BE67091D60E16D03]]></OPEN_FACT_ACCT_GROUP_ID>
</AD_ORG_CLOSING>

<AD_ORG_CLOSING>
  <AD_ORG_CLOSING_ID><![CDATA[9BEB1A2EC3884125B92D6A17007CCF58]]></AD_ORG_CLOSING_ID>
  <AD_CLIENT_ID><![CDATA[23C59575B9CF467C9620760EB255B389]]></AD_CLIENT_ID>
  <AD_ORG_ID><![CDATA[B843C30461EA4501935CB1D125C9C25A]]></AD_ORG_ID>
  <ISACTIVE><![CDATA[Y]]></ISACTIVE>
  <CREATED><![CDATA[2019-03-20 22:48:38.551315]]></CREATED>
  <CREATEDBY><![CDATA[100]]></CREATEDBY>
  <UPDATED><![CDATA[2019-03-20 22:48:38.551315]]></UPDATED>
  <UPDATEDBY><![CDATA[100]]></UPDATEDBY>
  <C_YEAR_ID><![CDATA[F2894E04910B4764B50A31BF018EBA8E]]></C_YEAR_ID>
  <AD_ORG_ACCTSCHEMA_ID><![CDATA[7583C0C800F14661B348A271ED276A14]]></AD_ORG_ACCTSCHEMA_ID>
  <REG_FACT_ACCT_GROUP_ID><![CDATA[7D679A720DF243E895AD80D48E4C46F7]]></REG_FACT_ACCT_GROUP_ID>
  <CLOSE_FACT_ACCT_GROUP_ID><![CDATA[12EF0002F6014E00BA9602DDFA0F07CB]]></CLOSE_FACT_ACCT_GROUP_ID>
  <OPEN_FACT_ACCT_GROUP_ID><![CDATA[95C7C7C7AE6741779C7F19D186E53B94]]></OPEN_FACT_ACCT_GROUP_ID>
</AD_ORG_CLOSING>

<AD_ORG_CLOSING>
  <AD_ORG_CLOSING_ID><![CDATA[A6ABA2E1B24847ABAAB3805D3FDC1983]]></AD_ORG_CLOSING_ID>
  <AD_CLIENT_ID><![CDATA[23C59575B9CF467C9620760EB255B389]]></AD_CLIENT_ID>
  <AD_ORG_ID><![CDATA[B843C30461EA4501935CB1D125C9C25A]]></AD_ORG_ID>
  <ISACTIVE><![CDATA[Y]]></ISACTIVE>
  <CREATED><![CDATA[2019-03-20 22:48:26.296703]]></CREATED>
  <CREATEDBY><![CDATA[100]]></CREATEDBY>
  <UPDATED><![CDATA[2019-03-20 22:48:26.296703]]></UPDATED>
  <UPDATEDBY><![CDATA[100]]></UPDATEDBY>
  <C_YEAR_ID><![CDATA[09E6CC5F7F6D4E8FA3DE5E120F7F9505]]></C_YEAR_ID>
  <AD_ORG_ACCTSCHEMA_ID><![CDATA[B6D5FF3A416C4371851ADA64EE9F0674]]></AD_ORG_ACCTSCHEMA_ID>
  <REG_FACT_ACCT_GROUP_ID><![CDATA[8762B93DE6C24747B6B1DF832BE678BC]]></REG_FACT_ACCT_GROUP_ID>
  <CLOSE_FACT_ACCT_GROUP_ID><![CDATA[B956BAF5D3594C149EF68A2F85C6A3D3]]></CLOSE_FACT_ACCT_GROUP_ID>
  <DIVIDEUP_FACT_ACCT_GROUP_ID><![CDATA[F41BD54131D443B69DFBA4F21D3ED0ED]]></DIVIDEUP_FACT_ACCT_GROUP_ID>
  <OPEN_FACT_ACCT_GROUP_ID><![CDATA[FF0DE8D8C7C44331861AB6191D49090D]]></OPEN_FACT_ACCT_GROUP_ID>
</AD_ORG_CLOSING>

<AD_ORG_CLOSING>
  <AD_ORG_CLOSING_ID><![CDATA[B0A0BBD1CD74425685C2223F9489FDAE]]></AD_ORG_CLOSING_ID>
  <AD_CLIENT_ID><![CDATA[23C59575B9CF467C9620760EB255B389]]></AD_CLIENT_ID>
  <AD_ORG_ID><![CDATA[B843C30461EA4501935CB1D125C9C25A]]></AD_ORG_ID>
  <ISACTIVE><![CDATA[Y]]></ISACTIVE>
  <CREATED><![CDATA[2019-03-20 22:48:52.433918]]></CREATED>
  <CREATEDBY><![CDATA[100]]></CREATEDBY>
  <UPDATED><![CDATA[2019-03-20 22:48:52.433918]]></UPDATED>
  <UPDATEDBY><![CDATA[100]]></UPDATEDBY>
  <C_YEAR_ID><![CDATA[8145E65C9078438681F06187E84E4C40]]></C_YEAR_ID>
  <AD_ORG_ACCTSCHEMA_ID><![CDATA[7583C0C800F14661B348A271ED276A14]]></AD_ORG_ACCTSCHEMA_ID>
  <REG_FACT_ACCT_GROUP_ID><![CDATA[BB5FB326CB5946E095EDE602FA0C2131]]></REG_FACT_ACCT_GROUP_ID>
  <CLOSE_FACT_ACCT_GROUP_ID><![CDATA[ED50731C45594B59B230E28BC2A3AFAF]]></CLOSE_FACT_ACCT_GROUP_ID>
  <OPEN_FACT_ACCT_GROUP_ID><![CDATA[EA439E86E9E141158200749292987353]]></OPEN_FACT_ACCT_GROUP_ID>
</AD_ORG_CLOSING>

<AD_ORG_CLOSING>
  <AD_ORG_CLOSING_ID><![CDATA[C707A3E430714D7FBBBF7D578DCBDF56]]></AD_ORG_CLOSING_ID>
  <AD_CLIENT_ID><![CDATA[23C59575B9CF467C9620760EB255B389]]></AD_CLIENT_ID>
  <AD_ORG_ID><![CDATA[B843C30461EA4501935CB1D125C9C25A]]></AD_ORG_ID>
  <ISACTIVE><![CDATA[Y]]></ISACTIVE>
  <CREATED><![CDATA[2019-03-20 22:48:56.683402]]></CREATED>
  <CREATEDBY><![CDATA[100]]></CREATEDBY>
  <UPDATED><![CDATA[2019-03-20 22:48:56.683402]]></UPDATED>
  <UPDATEDBY><![CDATA[100]]></UPDATEDBY>
  <C_YEAR_ID><![CDATA[BDDA2F60FE294C228DC7CFC3291D5ADF]]></C_YEAR_ID>
  <AD_ORG_ACCTSCHEMA_ID><![CDATA[B6D5FF3A416C4371851ADA64EE9F0674]]></AD_ORG_ACCTSCHEMA_ID>
  <REG_FACT_ACCT_GROUP_ID><![CDATA[E42919D3B5524432A71E151FDABF3234]]></REG_FACT_ACCT_GROUP_ID>
  <CLOSE_FACT_ACCT_GROUP_ID><![CDATA[5AAE270AF20B4A5A8EC2393485D7CE45]]></CLOSE_FACT_ACCT_GROUP_ID>
  <DIVIDEUP_FACT_ACCT_GROUP_ID><![CDATA[E76A79BF10CB410A8499EB749945DBF9]]></DIVIDEUP_FACT_ACCT_GROUP_ID>
  <OPEN_FACT_ACCT_GROUP_ID><![CDATA[767B8A16573146498E94D49C809993FB]]></OPEN_FACT_ACCT_GROUP_ID>
</AD_ORG_CLOSING>

<AD_ORG_CLOSING>
  <AD_ORG_CLOSING_ID><![CDATA[DCF310ED9D6C48819901DFD7C99CD66C]]></AD_ORG_CLOSING_ID>
  <AD_CLIENT_ID><![CDATA[23C59575B9CF467C9620760EB255B389]]></AD_CLIENT_ID>
  <AD_ORG_ID><![CDATA[B843C30461EA4501935CB1D125C9C25A]]></AD_ORG_ID>
  <ISACTIVE><![CDATA[Y]]></ISACTIVE>
  <CREATED><![CDATA[2021-03-29 21:06:23.524707]]></CREATED>
  <CREATEDBY><![CDATA[100]]></CREATEDBY>
  <UPDATED><![CDATA[2021-03-29 21:06:23.524707]]></UPDATED>
  <UPDATEDBY><![CDATA[100]]></UPDATEDBY>
  <C_YEAR_ID><![CDATA[3DEC6A414B294F648D05AB2A9F61EEC6]]></C_YEAR_ID>
  <AD_ORG_ACCTSCHEMA_ID><![CDATA[B6D5FF3A416C4371851ADA64EE9F0674]]></AD_ORG_ACCTSCHEMA_ID>
  <REG_FACT_ACCT_GROUP_ID><![CDATA[D7D98660921B47B58B3A4B0E563657D2]]></REG_FACT_ACCT_GROUP_ID>
  <CLOSE_FACT_ACCT_GROUP_ID><![CDATA[ADF781D290904E58AF01D3177DC71EB9]]></CLOSE_FACT_ACCT_GROUP_ID>
  <DIVIDEUP_FACT_ACCT_GROUP_ID><![CDATA[982A7F96774144F69CD86C1F285C6141]]></DIVIDEUP_FACT_ACCT_GROUP_ID>
  <OPEN_FACT_ACCT_GROUP_ID><![CDATA[BC869CA9676E4F5DB99C8B178BAC3FA2]]></OPEN_FACT_ACCT_GROUP_ID>
</AD_ORG_CLOSING>

<AD_ORG_CLOSING>
  <AD_ORG_CLOSING_ID><![CDATA[F9F5F3F6FE0C46C3B1532AD462A4DDEF]]></AD_ORG_CLOSING_ID>
  <AD_CLIENT_ID><![CDATA[23C59575B9CF467C9620760EB255B389]]></AD_CLIENT_ID>
  <AD_ORG_ID><![CDATA[B843C30461EA4501935CB1D125C9C25A]]></AD_ORG_ID>
  <ISACTIVE><![CDATA[Y]]></ISACTIVE>
  <CREATED><![CDATA[2021-03-29 21:06:14.799758]]></CREATED>
  <CREATEDBY><![CDATA[100]]></CREATEDBY>
  <UPDATED><![CDATA[2021-03-29 21:06:14.799758]]></UPDATED>
  <UPDATEDBY><![CDATA[100]]></UPDATEDBY>
  <C_YEAR_ID><![CDATA[D8185F72B57749869DC219CF2D1E863A]]></C_YEAR_ID>
  <AD_ORG_ACCTSCHEMA_ID><![CDATA[B6D5FF3A416C4371851ADA64EE9F0674]]></AD_ORG_ACCTSCHEMA_ID>
  <REG_FACT_ACCT_GROUP_ID><![CDATA[C5E7D75063F546B287567775AD7DA88B]]></REG_FACT_ACCT_GROUP_ID>
  <CLOSE_FACT_ACCT_GROUP_ID><![CDATA[89487C4C0A884453803BE0F3FA49D10E]]></CLOSE_FACT_ACCT_GROUP_ID>
  <DIVIDEUP_FACT_ACCT_GROUP_ID><![CDATA[57D6293638454D2FAEF5D8307CB3F5CD]]></DIVIDEUP_FACT_ACCT_GROUP_ID>
  <OPEN_FACT_ACCT_GROUP_ID><![CDATA[AB774BC27CC044F487876E35D6574B3F]]></OPEN_FACT_ACCT_GROUP_ID>
</AD_ORG_CLOSING>

<AD_ORG_CLOSING>
  <AD_ORG_CLOSING_ID><![CDATA[FA7E1A53B38344FCAE0BC5A75C548785]]></AD_ORG_CLOSING_ID>
  <AD_CLIENT_ID><![CDATA[23C59575B9CF467C9620760EB255B389]]></AD_CLIENT_ID>
  <AD_ORG_ID><![CDATA[B843C30461EA4501935CB1D125C9C25A]]></AD_ORG_ID>
  <ISACTIVE><![CDATA[Y]]></ISACTIVE>
  <CREATED><![CDATA[2019-03-20 22:48:13.868739]]></CREATED>
  <CREATEDBY><![CDATA[100]]></CREATEDBY>
  <UPDATED><![CDATA[2019-03-20 22:48:13.868739]]></UPDATED>
  <UPDATEDBY><![CDATA[100]]></UPDATEDBY>
  <C_YEAR_ID><![CDATA[BE903865711D408390B24C366B6C4099]]></C_YEAR_ID>
  <AD_ORG_ACCTSCHEMA_ID><![CDATA[B6D5FF3A416C4371851ADA64EE9F0674]]></AD_ORG_ACCTSCHEMA_ID>
  <REG_FACT_ACCT_GROUP_ID><![CDATA[60A17E5CE13441ACA43B1B0216CC404F]]></REG_FACT_ACCT_GROUP_ID>
  <CLOSE_FACT_ACCT_GROUP_ID><![CDATA[F7BE3463365B41D2BD4C7A960127A6D4]]></CLOSE_FACT_ACCT_GROUP_ID>
  <DIVIDEUP_FACT_ACCT_GROUP_ID><![CDATA[11142E8F568349BAB53AB95CFB545A3D]]></DIVIDEUP_FACT_ACCT_GROUP_ID>
  <OPEN_FACT_ACCT_GROUP_ID><![CDATA[F2E8A2E8F4CD493B844F59DC970E83D7]]></OPEN_FACT_ACCT_GROUP_ID>
</AD_ORG_CLOSING>

<AD_ORG_CLOSING>
  <AD_ORG_CLOSING_ID><![CDATA[FB815995B904441FAF9107D760951DB0]]></AD_ORG_CLOSING_ID>
  <AD_CLIENT_ID><![CDATA[23C59575B9CF467C9620760EB255B389]]></AD_CLIENT_ID>
  <AD_ORG_ID><![CDATA[2E60544D37534C0B89E765FE29BC0B43]]></AD_ORG_ID>
  <ISACTIVE><![CDATA[Y]]></ISACTIVE>
  <CREATED><![CDATA[2019-03-20 22:48:30.527961]]></CREATED>
  <CREATEDBY><![CDATA[100]]></CREATEDBY>
  <UPDATED><![CDATA[2019-03-20 22:48:30.527961]]></UPDATED>
  <UPDATEDBY><![CDATA[100]]></UPDATEDBY>
  <C_YEAR_ID><![CDATA[31E93936301446F7BDEAB5DBF7EC3912]]></C_YEAR_ID>
  <AD_ORG_ACCTSCHEMA_ID><![CDATA[B6D5FF3A416C4371851ADA64EE9F0674]]></AD_ORG_ACCTSCHEMA_ID>
  <REG_FACT_ACCT_GROUP_ID><![CDATA[A2092420621B4087BB51582D4E7156DD]]></REG_FACT_ACCT_GROUP_ID>
  <CLOSE_FACT_ACCT_GROUP_ID><![CDATA[5002410F84464980AF256C2F3DEF68A4]]></CLOSE_FACT_ACCT_GROUP_ID>
  <DIVIDEUP_FACT_ACCT_GROUP_ID><![CDATA[31B03D12B5534842949EC9554AEDA298]]></DIVIDEUP_FACT_ACCT_GROUP_ID>
  <OPEN_FACT_ACCT_GROUP_ID><![CDATA[9458E98FC21244A786695ACB0DE7CFD3]]></OPEN_FACT_ACCT_GROUP_ID>
</AD_ORG_CLOSING>

</data>
